xbrl2rdf/DtsProcessor.py
xbrl2rdf/FileSource.py
xbrl2rdf/InstanceProcessor.py
xbrl2rdf/LinkbaseProcessor.py
xbrl2rdf/PackageManager.py
xbrl2rdf/SchemaProcessor.py
xbrl2rdf/__init__.py
xbrl2rdf/const.py
xbrl2rdf/utilfunctions.py
xbrl2rdf/xbrl2rdf.py
xbrl2rdf-0.1.0.dist-info/AUTHORS.rst
xbrl2rdf-0.1.0.dist-info/LICENSE
xbrl2rdf-0.1.0.dist-info/METADATA
xbrl2rdf-0.1.0.dist-info/WHEEL
xbrl2rdf-0.1.0.dist-info/entry_points.txt
xbrl2rdf-0.1.0.dist-info/top_level.txt
xbrl2rdf-0.1.0.dist-info/RECORD
