Metadata-Version: 2.1
Name: xbrl2rdf
Version: 0.1.0
Summary: Python package to convert XBRL instance and taxonomy files to RDF
Home-page: https://github.com/wjwillemse/xbrl2rdf
Author: Willem Jan Willemse
Author-email: w.j.willemse@xs4all.nl
License: MIT license
Keywords: xbrl2rdf
Platform: UNKNOWN
Classifier: Development Status :: 2 - Pre-Alpha
Classifier: Intended Audience :: Developers
Classifier: License :: OSI Approved :: MIT License
Classifier: Natural Language :: English
Classifier: Programming Language :: Python :: 3
Classifier: Programming Language :: Python :: 3.5
Classifier: Programming Language :: Python :: 3.6
Classifier: Programming Language :: Python :: 3.7
Classifier: Programming Language :: Python :: 3.8
Requires-Python: >=3.5
Requires-Dist: Click (>=7.0)
Requires-Dist: rdflib
Requires-Dist: lxml
